<?xml version="1.0" encoding="utf-8" ?>
<dwsync>
<file name="chart.esm.js" server="ftp.grafcontrol2.hospedagemdesites.ws/public_html/" local="133450326134963757" remote="133450330600000000" Dst="0" />
<file name="chart.min.js" server="ftp.grafcontrol2.hospedagemdesites.ws/public_html/" local="133450326136535797" remote="133450330600000000" Dst="0" />
<file name="chart.mjs" server="ftp.grafcontrol2.hospedagemdesites.ws/public_html/" local="133450326137899856" remote="133450330610000000" Dst="0" />
<file name="helpers.esm.js" server="ftp.grafcontrol2.hospedagemdesites.ws/public_html/" local="133450326138295948" remote="133450330610000000" Dst="0" />
<file name="helpers.mjs" server="ftp.grafcontrol2.hospedagemdesites.ws/public_html/" local="133450326138697088" remote="133450330610000000" Dst="0" />
<file name="chart.min.js" server="ftp.grafcontrol.com.br/public_html/" local="133450326136535797" remote="133452954000000000" Dst="0" />
<file name="chart.esm.js" server="ftp.grafcontrol.com.br/public_html/" local="133450326134963757" remote="133452954000000000" Dst="0" />
<file name="chart.mjs" server="ftp.grafcontrol.com.br/public_html/" local="133450326137899856" remote="133452954000000000" Dst="0" />
<file name="helpers.esm.js" server="ftp.grafcontrol.com.br/public_html/" local="133450326138295948" remote="133452954000000000" Dst="0" />
<file name="helpers.mjs" server="ftp.grafcontrol.com.br/public_html/" local="133450326138697088" remote="133452954000000000" Dst="0" />
</dwsync>